{
  "dependencies": [],
  "tasks": {
    "5B74DD8F5B376852": {
      "type": "heracles:item",
      "item": "#handcrafted:side_tables",
      "amount": 1,
      "collection": "AUTOMATIC",
      "title": "Any #handcrafted:side_tables"
    }
  },
  "rewards": {
    "6F0DD2832A676A30": {
      "item": {
        "id": "minecraft:iron_block",
        "count": 1
      },
      "type": "heracles:item"
    }
  },
  "display": {
    "subtitle": {
      "text": ""
    },
    "description": [
      "<task task=\"5B74DD8F5B376852\" quest=\"2816C536AA7A650D\"/>",
      "<hr/>",
      "<hr/>",
      "<reward reward=\"6F0DD2832A676A30\" quest=\"2816C536AA7A650D\"/>"
    ],
    "groups": {
      " ยง5Furniture": {
        "position": [
          -16,
          -144
        ]
      }
    },
    "icon": {
      "item": {
        "id": "handcrafted:oak_side_table",
        "count": 1
      },
      "type": "heracles:item"
    },
    "icon_background": "heracles:textures/gui/quest_backgrounds/default.png",
    "title": {
      "translate": "Side Tables"
    }
  },
  "settings": {
    "showDependencyArrow": true,
    "repeatable": false,
    "autoClaimRewards": false,
    "individual_progress": false,
    "hidden": "LOCKED",
    "unlockNotification": false
  }
}