{
  "dependencies": [],
  "tasks": {
    "178F76F92062C167": {
      "icon": {
        "item": {
          "id": "minecraft:reinforced_deepslate",
          "count": 1
        },
        "type": "heracles:item"
      },
      "from": "minecraft:overworld",
      "to": "deeperdarker:otherside",
      "title": "Enter &3The Otherside",
      "type": "heracles:changed_dimension"
    }
  },
  "rewards": {
    "65CA22F512A28DD1": {
      "item": {
        "id": "minecraft:recovery_compass",
        "count": 1
      },
      "type": "heracles:item"
    },
    "06CEBE2F2243DD35": {
      "item": {
        "id": "deeperdarker:warden_carapace",
        "count": 4
      },
      "type": "heracles:item"
    },
    "0F818E53C9D7D6ED": {
      "xptype": "LEVEL",
      "amount": 10,
      "type": "heracles:xp"
    }
  },
  "display": {
    "subtitle": {
      "translate": "Click on this quest to view the description and read the portal activation guide."
    },
    "description": [
      "<subtitle id=\"6DF9CE1B78FEF4E4\" bold=\"true\" centered=\"true\" color=\"lightgray\"/>",
      "<hr/>",
      "<task task=\"178F76F92062C167\" quest=\"6DF9CE1B78FEF4E4\"/>",
      "<hr/>",
      "To enter &&1The Otherside&&r, locate the &&3Ancient City&&r and defeat the &&3Warden&&r.",
      "<br/>",
      "When killed, &&3Warden &&rdrops the &&5Heart of the Deep&&r.",
      "<br/>",
      "The portal is located in the center of &&3Ancient City&&r.",
      "<br/>",
      "Right click the &&3Reinforced Deepslate &&rwith the &&5Heart of the Deep &&rto activate the portal.",
      "<hr/>",
      "<reward reward=\"0F818E53C9D7D6ED\" quest=\"6DF9CE1B78FEF4E4\"/>",
      "<reward reward=\"06CEBE2F2243DD35\" quest=\"6DF9CE1B78FEF4E4\"/>",
      "<reward reward=\"65CA22F512A28DD1\" quest=\"6DF9CE1B78FEF4E4\"/>"
    ],
    "groups": {
      " ยง2Dimensions": {
        "position": [
          -96,
          -32
        ]
      }
    },
    "icon": {
      "item": {
        "id": "minecraft:reinforced_deepslate",
        "count": 1
      },
      "type": "heracles:item"
    },
    "icon_background": "heracles:textures/gui/quest_backgrounds/octagons.png",
    "title": {
      "translate": "Enter &3The Otherside"
    }
  },
  "settings": {
    "showDependencyArrow": true,
    "repeatable": false,
    "autoClaimRewards": false,
    "individual_progress": false,
    "hidden": "LOCKED",
    "unlockNotification": false
  }
}